{"OFFICERS": {"2016": {"treasurer": "corey ford", "president": "jeff mcgovern", "vice president": "vignesh kalidas"}, "2003": {"distro of the year": "ubuntu", "webmaster": "keith", "president": "red wagner", "master of what\u00e2\u0080\u0099s going on": "jimson xu", "secretary": "rowen & seth", "vice president": "derek", "treasurer": "david sharp"}, "2004": {"distro of the year": "ubuntu", "webmaster": "keith", "president": "red wagner", "master of what\u00e2\u0080\u0099s going on": "jimson xu", "secretary": "rowen & seth", "vice president": "derek", "treasurer": "david sharp"}, "2005": {"distro of the year": "ubuntu", "webmaster": "keith", "president": "red wagner", "master of what\u00e2\u0080\u0099s going on": "jimson xu", "secretary": "rowen & seth", "vice president": "derek", "treasurer": "david sharp"}, "2006": {"distro of the year": "ubuntu", "webmaster": "keith", "president": "red wagner", "master of what\u00e2\u0080\u0099s going on": "jimson xu", "secretary": "rowen & seth", "vice president": "derek", "treasurer": "david sharp"}, "2007": {"return of the san and http": "//mirrors.calpoly.edu", "webmaster": "nat welch", "president": "josh lange", "master of what\u00e2\u0080\u0099s going on": "michelle khuu", "secretary": "nat welch", "vice president": "erik carpenter", "treasurer": "mark gius"}, "2008": {"vp": "timothy goya (tuxdev)", "president": "austin hendrix (trainman)"}, "2009": {"vp": "timothy goya (tuxdev)", "president": "austin hendrix (trainman)"}, "2010": {"president": "corey farwell", "vice president": "michael lekander"}, "2011": {"distro of the year": "linux mint", "president": "michael lekander"}, "2012": {"secretary": "kevin stein", "\u00e2\u0080\u009cwebmaster\u00e2\u0080\u009d": "michael lekander", "president": "corey farwell", "vice president": "corey ford"}, "2013": {"secretary/webmaster": "michael lekander", "chief party coordinator": "corey farwell", "treasurer": "robin choudhury", "president": "corey ford", "vice president": "peter faiman"}, "2014": {"industrial relations": "corey ford", "treasurer": "robin choudhury", "president": "jacob hladky", "vice president": "vignesh kalidas"}, "2015": {"treasurer": "corey ford", "president": "jeff mcgovern", "vice president": "vignesh kalidas"}}}